django_resto/__init__.py
django_resto/http_server.py
django_resto/models.py
django_resto/settings.py
django_resto/storage.py
django_resto/test_get_setting.py
django_resto/test_http_server.py
django_resto/test_regression.py
django_resto/test_settings.py
django_resto/test_storage.py
django_resto/tests.py
django_resto-1.3.dist-info/DESCRIPTION.rst
django_resto-1.3.dist-info/METADATA
django_resto-1.3.dist-info/RECORD
django_resto-1.3.dist-info/WHEEL
django_resto-1.3.dist-info/metadata.json
django_resto-1.3.dist-info/pbr.json
django_resto-1.3.dist-info/top_level.txt
