Metadata-Version: 2.0
Name: django-resto
Version: 1.3
Summary: REplicated STOrage for Django, file backends that mirror media files to several servers over HTTP
Home-page: https://github.com/aaugustin/django-resto
Author: Aymeric Augustin
Author-email: aymeric.augustin@m4x.org
License: BSD
Download-URL: http://pypi.python.org/pypi/django-resto
Platform: all
Classifier: Development Status :: 5 - Production/Stable
Classifier: Environment :: Web Environment
Classifier: Framework :: Django
Classifier: Intended Audience :: Developers
Classifier: License :: OSI Approved :: BSD License
Classifier: Operating System :: OS Independent
Classifier: Programming Language :: Python
Classifier: Programming Language :: Python :: 2
Classifier: Programming Language :: Python :: 2.7
Classifier: Programming Language :: Python :: 3
Classifier: Programming Language :: Python :: 3.2
Classifier: Programming Language :: Python :: 3.3
Classifier: Programming Language :: Python :: 3.4
Classifier: Programming Language :: Python :: 3.5
